neon_enclosure/__init__.py
neon_enclosure/__main__.py
neon_enclosure/cli.py
neon_enclosure/service.py
neon_enclosure/utils.py
neon_enclosure/admin/__init__.py
neon_enclosure/admin/__main__.py
neon_enclosure/admin/service.py
neon_enclosure-1.8.0.dist-info/LICENSE.md
neon_enclosure-1.8.0.dist-info/METADATA
neon_enclosure-1.8.0.dist-info/WHEEL
neon_enclosure-1.8.0.dist-info/entry_points.txt
neon_enclosure-1.8.0.dist-info/top_level.txt
neon_enclosure-1.8.0.dist-info/RECORD
