Metadata-Version: 2.1
Name: neon-enclosure
Version: 1.8.0
Summary: Neon Enclosure Module
Home-page: https://github.com/NeonGeckoCom/neon-enclosure
Author: Neongecko
Author-email: developers@neon.ai
License: BSD-3-Clause
License-File: LICENSE.md
Requires-Dist: ovos-phal>=0.0.5,~=0.0
Requires-Dist: neon-utils[network,signal]>=1.12.1,~=1.12
Requires-Dist: ovos-utils>=0.0.32,~=0.0
Requires-Dist: click~=8.0
Requires-Dist: click-default-group~=1.2
Requires-Dist: ovos-bus-client>=0.0.8,~=0.0
Provides-Extra: docker
Requires-Dist: ovos-phal-plugin-homeassistant~=0.1; extra == "docker"
Requires-Dist: ovos-phal-plugin-notification-widgets~=1.0.0; extra == "docker"
Requires-Dist: ovos-phal-plugin-color-scheme-manager~=1.0.0; extra == "docker"
Requires-Dist: ovos-phal-plugin-configuration-provider~=1.0.0; extra == "docker"
Requires-Dist: ovos-phal-plugin-connectivity-events~=0.1; extra == "docker"
Requires-Dist: ovos-phal-plugin-oauth~=0.1; extra == "docker"
Requires-Dist: neon-phal-plugin-monitoring~=0.0.1; extra == "docker"
